LICENSE.txt
MANIFEST.in
README.md
setup.py
eiger_viewer/__init__.py
eiger_viewer/main.py
eiger_viewer.egg-info/PKG-INFO
eiger_viewer.egg-info/SOURCES.txt
eiger_viewer.egg-info/dependency_links.txt
eiger_viewer.egg-info/entry_points.txt
eiger_viewer.egg-info/requires.txt
eiger_viewer.egg-info/top_level.txt
eiger_viewer/modules/__init__.py
eiger_viewer/modules/viewer.py
eiger_viewer/ui/__init__.py
eiger_viewer/ui/viewerGUI.py
eiger_viewer/utils/__init__.py
eiger_viewer/utils/exception_handler.py
eiger_viewer/utils/file_manager.py
eiger_viewer/utils/hdf5_manager.py
eiger_viewer/utils/image_processor.py
eiger_viewer/utils/pyqt_utils.py