Metadata-Version: 2.1
Name: eiger-viewer
Version: 0.1.0
Summary: EIGER Viewer
Home-page: https://github.com/biocatiit
Author: BioCAT
Author-email: biocat@lethocerus.biol.iit.edu
License: UNKNOWN
Keywords: eiger viewer,biocat
Platform: UNKNOWN
Classifier: Development Status :: 3 - Alpha
Classifier: Environment :: X11 Applications :: Qt
Classifier: Intended Audience :: Science/Research
Classifier: Natural Language :: English
Classifier: Operating System :: Other OS
Classifier: Programming Language :: Python
Classifier: Programming Language :: Cython
Classifier: Topic :: Scientific/Engineering :: Bio-Informatics
License-File: LICENSE.txt
